pygramcl/__init__.py
pygramcl/checker.py
pygramcl/client.py
pygramcl/download.py
pygramcl/fakemail.py
pygramcl/gemini.py
pygramcl/guest.py
pygramcl/live.py
pygramcl/parser.py
pygramcl/photo.py
pygramcl/types.py
pygramcl/utils.py
pygramcl/video.py
pygramcl-1.3.dist-info/licenses/LICENSE
pygramcl-1.3.dist-info/METADATA
pygramcl-1.3.dist-info/WHEEL
pygramcl-1.3.dist-info/top_level.txt
pygramcl-1.3.dist-info/RECORD
