Metadata-Version: 2.4
Name: pygramcl
Version: 1.3
Summary: Python wrapper for Instagram Client(s)
Author-email: pygramcl <support@pygramcl.com>
License: MIT License
Project-URL: Homepage, https://pypi.org/project/pygramcl
Project-URL: Source, https://pypi.org/project/pygramcl
Keywords: pygramcl,instagram,instagram-api,instagram-sdk,instagram-client,instagram-web-api,instagram-private-api
Classifier: Programming Language :: Python :: 3
Classifier: License :: OSI Approved :: MIT License
Classifier: Operating System :: OS Independent
Requires-Python: >=3.7
License-File: LICENSE
Requires-Dist: requests
Requires-Dist: Pillow
Dynamic: license-file
